setup.py
as_prob_distributions_jun2024/Binomialdistribution.py
as_prob_distributions_jun2024/Binomialdistribution_challenge.py
as_prob_distributions_jun2024/Gaussiandistribution.py
as_prob_distributions_jun2024/Generaldistribution.py
as_prob_distributions_jun2024/__init__.py
as_prob_distributions_jun2024.egg-info/PKG-INFO
as_prob_distributions_jun2024.egg-info/SOURCES.txt
as_prob_distributions_jun2024.egg-info/dependency_links.txt
as_prob_distributions_jun2024.egg-info/not-zip-safe
as_prob_distributions_jun2024.egg-info/top_level.txt