Metadata-Version: 2.1
Name: as-prob-distributions-jun2024
Version: 0.0.1
Summary: Gaussian and Binomial distribution
